logreg/__init__.py
logreg/data/logreg
logreg-0.1.0.dist-info/LICENSE
logreg-0.1.0.dist-info/METADATA
logreg-0.1.0.dist-info/WHEEL
logreg-0.1.0.dist-info/top_level.txt
logreg-0.1.0.dist-info/RECORD
