Metadata-Version: 2.1
Name: logreg
Version: 0.1.0
Summary: A logisticregression model for predicting license short_name
Home-page: UNKNOWN
Author: Sushant Kumar
Author-email: sushantmishra02102002@gmail.com
License: UNKNOWN
Platform: UNKNOWN
Requires-Python: >=3.5
